MyMessenger-0.3.3.dist-info/DESCRIPTION.rst
MyMessenger-0.3.3.dist-info/METADATA
MyMessenger-0.3.3.dist-info/RECORD
MyMessenger-0.3.3.dist-info/WHEEL
MyMessenger-0.3.3.dist-info/entry_points.txt
MyMessenger-0.3.3.dist-info/metadata.json
MyMessenger-0.3.3.dist-info/top_level.txt
my_messenger/__init__.py
my_messenger/utils.py
my_messenger/client/__init__.py
my_messenger/client/client_console.py
my_messenger/client/client_gui.py
my_messenger/client/core.py
my_messenger/client/errors.py
my_messenger/client/handlers.py
my_messenger/client/gui/__init__.py
my_messenger/client/gui/dialogs.py
my_messenger/client/gui/main.py
my_messenger/client/gui/utils.py
my_messenger/client/gui/img/icon/b.jpg
my_messenger/client/gui/img/icon/i.jpg
my_messenger/client/gui/img/icon/u.jpg
my_messenger/client/gui/img/smile/ab.gif
my_messenger/client/gui/img/smile/ac.gif
my_messenger/client/gui/img/smile/ai.gif
my_messenger/client/gui/loader/__init__.py
my_messenger/client/gui/loader/loader.py
my_messenger/client/gui/repo/__init__.py
my_messenger/client/gui/repo/models.py
my_messenger/client/gui/repo/repo.py
my_messenger/client/gui/ui/AboutDialog.py
my_messenger/client/gui/ui/ConnectDialog.py
my_messenger/client/gui/ui/MainWindow.py
my_messenger/client/gui/ui/ProfileDialog.py
my_messenger/client/gui/ui/__init__.py
my_messenger/jim/__init__.py
my_messenger/jim/config.py
my_messenger/jim/core.py
my_messenger/jim/exceptions.py
my_messenger/jim/test_core.py
my_messenger/jim/test_exceptions.py
my_messenger/jim/test_utils.py
my_messenger/jim/utils.py
my_messenger/logger/__init__.py
my_messenger/logger/config.py
my_messenger/logger/decorators.py
my_messenger/logger/test_decorators.py
my_messenger/mongo_db/__init__.py
my_messenger/mongo_db/config.py
my_messenger/mongo_db/core.py
my_messenger/mongo_db/test_core.py
my_messenger/server/__init__.py
my_messenger/server/server.py
my_messenger/server/chat/__init__.py
my_messenger/server/chat/chat.py
my_messenger/server/repo/__init__.py
my_messenger/server/repo/errors.py
my_messenger/server/repo/models.py
my_messenger/server/repo/repo.py
my_messenger/server/repo/test_errors.py
my_messenger/server/repo/test_repo.py
